{
  "lastSync": "2026-02-21T14:00:41+01:00",
  "heartbeats": {
    "main": {
      "lastCheck": "2026-02-21T14:00:00+01:00",
      "status": "ok"
    },
    "plaza-marketing": {
      "lastCheck": "2026-02-21T13:06:15+01:00",
      "status": "ok"
    },
    "clea": {
      "lastCheck": "2026-02-21T13:35:55+01:00",
      "status": "ok"
    }
  },
  "recentActivity": [
    {
      "time": "11:36",
      "agent": "Claudia",
      "action": "Tâche automatisée"
    },
    {
      "time": "11:37",
      "agent": "Claudia",
      "action": "Tâche automatisée"
    },
    {
      "time": "11:37",
      "agent": "Claudia",
      "action": "Tâche automatisée"
    },
    {
      "time": "11:37",
      "agent": "Claudia",
      "action": "Tâche automatisée"
    },
    {
      "time": "11:37",
      "agent": "Claudia",
      "action": "Tâche automatisée"
    }
  ],
  "tokenUsage": {
    "today": {
      "input": 55,
      "output": 1263,
      "cost": 0.09555000000000000000
    }
  }
}
